kcspkg/__init__.py
tawashipkg/__init__.py
tawashipkg-1.0.1.dist-info/METADATA
tawashipkg-1.0.1.dist-info/WHEEL
tawashipkg-1.0.1.dist-info/top_level.txt
tawashipkg-1.0.1.dist-info/RECORD
